cached_ipaddress/__init__.py
cached_ipaddress/_compat.py
cached_ipaddress/ipaddress.cpython-39-x86_64-linux-gnu.so
cached_ipaddress/ipaddress.pxd
cached_ipaddress/ipaddress.py
cached_ipaddress/py.typed
cached_ipaddress/backports/__init__.py
cached_ipaddress-0.10.0.dist-info/LICENSE
cached_ipaddress-0.10.0.dist-info/METADATA
cached_ipaddress-0.10.0.dist-info/WHEEL
cached_ipaddress-0.10.0.dist-info/RECORD
