Metadata-Version: 2.3
Name: cached-ipaddress
Version: 0.10.0
Summary: Cache construction of ipaddress objects
License: MIT
Author: J. Nick Koston
Author-email: nick@koston.org
Requires-Python: >=3.8,<4.0
Classifier: Development Status :: 5 - Production/Stable
Classifier: Intended Audience :: Developers
Classifier: License :: OSI Approved :: MIT License
Classifier: Natural Language :: English
Classifier: Operating System :: OS Independent
Classifier: Programming Language :: Python :: 3
Classifier: Programming Language :: Python :: 3.8
Classifier: Programming Language :: Python :: 3.9
Classifier: Programming Language :: Python :: 3.10
Classifier: Programming Language :: Python :: 3.11
Classifier: Programming Language :: Python :: 3.12
Classifier: Programming Language :: Python :: 3.13
Classifier: Topic :: Software Development :: Libraries
Requires-Dist: propcache (>=0.0.0)
Project-URL: Bug Tracker, https://github.com/bluetooth-devices/cached-ipaddress/issues
Project-URL: Changelog, https://github.com/bluetooth-devices/cached-ipaddress/blob/main/CHANGELOG.md
Project-URL: Repository, https://github.com/bluetooth-devices/cached-ipaddress
